clipyth/__init__.py
clipyth/__main__.py
clipyth-1.0.4.dist-info/LICENSE
clipyth-1.0.4.dist-info/METADATA
clipyth-1.0.4.dist-info/WHEEL
clipyth-1.0.4.dist-info/entry_points.txt
clipyth-1.0.4.dist-info/top_level.txt
clipyth-1.0.4.dist-info/RECORD
