Metadata-Version: 2.2
Name: clipyth
Version: 1.0.4
Summary: A simple CLI (Command Line Interface) to create python projects with different templates
Home-page: https://github.com/Elabsurdo984/clipyth.git
Author: Elabsurdo984
Author-email: matiassfernandez00@gmail.com
License: MIT
Project-URL: Source, https://github.com/Elabsurdo984/clipyth
Classifier: License :: OSI Approved :: MIT License
Classifier: Natural Language :: English
Classifier: Programming Language :: Python :: 3 :: Only
Classifier: Programming Language :: Python :: 3
Classifier: Programming Language :: Python :: 3.8
Classifier: Programming Language :: Python :: 3.9
Classifier: Programming Language :: Python :: 3.10
Classifier: Programming Language :: Python :: 3.11
Classifier: Programming Language :: Python :: 3.12
Classifier: Programming Language :: Python :: 3.13
Classifier: Programming Language :: Python
Classifier: Topic :: Software Development
Requires-Python: >=3.8
License-File: LICENSE
Dynamic: author
Dynamic: author-email
Dynamic: classifier
Dynamic: description
Dynamic: description-content-type
Dynamic: home-page
Dynamic: license
Dynamic: project-url
Dynamic: requires-python
Dynamic: summary
